setup.py
bpbroker/__init__.py
bpbroker/api.py
bpbroker/cli.py
bpbroker/config.py
bpbroker/discover.py
bpbroker/dummy_api.crt
bpbroker/dummy_api.key
bpbroker/install.py
bpbroker/ping.py
bpbroker/server.py
bpbroker/services.py
bpbroker/shell.py
bpbroker/worker.py
bpbroker.egg-info/PKG-INFO
bpbroker.egg-info/SOURCES.txt
bpbroker.egg-info/dependency_links.txt
bpbroker.egg-info/entry_points.txt
bpbroker.egg-info/pbr.json
bpbroker.egg-info/requires.txt
bpbroker.egg-info/top_level.txt
bpclient/__init__.py
bpclient/cli.py
bpclient/discover.py
bpclient/execute.py
bpclient/output.py
bpclient/ping.py
bpclient/services.py
bpclient/shell.py
bpmailer/__init__.py
bpmailer/cli.py
bpmailer/config.py
bpmailer/mailer.py
bpmailer/shell.py