Metadata-Version: 1.0
Name: bpbroker
Version: 0.22
Summary: CenturyLink Cloud Blueprint Broker Service Tools
Home-page: https://github.com/CenturyLinkCloud/Ecosystem/tree/master/Blueprints/Blueprint%20Broker
Author: Keith Resar
Author-email: Keith.Resar@CenturyLinkCloud.com
License: UNKNOWN
Keywords: CenturyLink Cloud Blueprint Broker
Platform: UNKNOWN
